Metadata-Version: 2.1
Name: modomx
Version: 0.1.1
Summary: Omxplayer wrapper compatible with Python 2.x
Home-page: https://github.com/mmprestes/modomx
Author: Marcelo Prestes
Author-email: marcelo.prestes@gmail.com
License: UNKNOWN
Platform: UNKNOWN
Classifier: Programming Language :: Python :: 2
Classifier: Programming Language :: Python :: 2.7
Classifier: License :: OSI Approved :: MIT License
Classifier: Operating System :: OS Independent
Requires-Python: >=2.7, <3
